etl_jobs/__init__.py
etl_jobs/configuration/api_raw_data/__init__.py
etl_jobs/configuration/api_raw_data/apis.py
etl_jobs/jobs/extract/__init__.py
etl_jobs/jobs/extract/elt_data_api.py
etl_jobs/util/extract/__init__.py
etl_jobs/util/extract/api.py
etl_jobs/util/load/__init__.py
etl_jobs/util/load/delta_local.py
etl_jobs/util/load/delta_spark.py
etl_jobs/util/transform/__init__.py
etl_jobs/util/transform/gold_sales.py
etl_jobs/util/transform/polar_bear.py
etl_jobs-0.1.13.dist-info/METADATA
etl_jobs-0.1.13.dist-info/WHEEL
etl_jobs-0.1.13.dist-info/RECORD
