Metadata-Version: 2.1
Name: etl-jobs
Version: 0.1.13
Summary: 
Author: Brian L
Author-email: bclipp770@gmail.com
Requires-Python: >=3.9,<4.0
Classifier: Programming Language :: Python :: 3
Classifier: Programming Language :: Python :: 3.9
Classifier: Programming Language :: Python :: 3.10
Classifier: Programming Language :: Python :: 3.11
Requires-Dist: deltalake (>=0.9.0,<0.10.0)
Requires-Dist: polars (>=0.17.14,<0.18.0)
Requires-Dist: pyspark (>=3.4.0,<4.0.0)
Requires-Dist: requests (>=2.30.0,<3.0.0)
